edatk/__init__.py
edatk/_auto_eda.py
edatk/_core.py
edatk/_html_report/_report_builder.py
edatk/_html_report/_template_ops.py
edatk/_html_report/report_template.html
edatk/_modeling/_cross_val_custom.py
edatk/_multi_variable/_auto_eda_multi_variable.py
edatk/_multi_variable/_visuals.py
edatk/_single_variable/_auto_eda_single_variable.py
edatk/_single_variable/_cardinality_reduction.py
edatk/_single_variable/_summary_statistics.py
edatk/_single_variable/_visuals.py
edatk-0.0.8.dist-info/LICENSE
edatk-0.0.8.dist-info/METADATA
edatk-0.0.8.dist-info/WHEEL
edatk-0.0.8.dist-info/top_level.txt
edatk-0.0.8.dist-info/RECORD
