Metadata-Version: 2.1
Name: edatk
Version: 0.0.8
Summary: edatk: python exploratory data analysis toolkit
Home-page: https://github.com/edatk/edatk/
Author: Barrett Studdard
Author-email: barrettstuddard@gmail.com
License: UNKNOWN
Platform: UNKNOWN
Classifier: Programming Language :: Python :: 3.9
Classifier: License :: OSI Approved :: GNU General Public License v3 (GPLv3)
Requires-Python: >=3.9
Requires-Dist: seaborn (>=0.11)
Requires-Dist: numpy (>=1.20)
Requires-Dist: matplotlib (>=3.4.2)
Requires-Dist: pandas (>=1.2.4)
Requires-Dist: jinja2 (>=3.0.1)
Requires-Dist: scipy (>=1.6.3)
Requires-Dist: scikit-learn (>=0.24.2)
